ApacheServer24ZhongwenWendang/README.md
ApacheServer24ZhongwenWendang/__init__.py
ApacheServer24ZhongwenWendang/__main__.py
ApacheServer24ZhongwenWendang/file.epub
ApacheServer24ZhongwenWendang/index.html
ApacheServer24ZhongwenWendang/css/__init__.py
ApacheServer24ZhongwenWendang/css/annotations.css
ApacheServer24ZhongwenWendang/css/main.css
ApacheServer24ZhongwenWendang/css/normalize.css
ApacheServer24ZhongwenWendang/css/popup.css
ApacheServer24ZhongwenWendang/font/__init__.py
ApacheServer24ZhongwenWendang/font/fontello.eot
ApacheServer24ZhongwenWendang/font/fontello.svg
ApacheServer24ZhongwenWendang/font/fontello.ttf
ApacheServer24ZhongwenWendang/font/fontello.woff
ApacheServer24ZhongwenWendang/img/__init__.py
ApacheServer24ZhongwenWendang/img/annotator-glyph-sprite.png
ApacheServer24ZhongwenWendang/img/annotator-icon-sprite.png
ApacheServer24ZhongwenWendang/img/apple-touch-icon.png
ApacheServer24ZhongwenWendang/img/cancelfullscreen.png
ApacheServer24ZhongwenWendang/img/close.png
ApacheServer24ZhongwenWendang/img/fullscreen.png
ApacheServer24ZhongwenWendang/img/loader.gif
ApacheServer24ZhongwenWendang/img/menu-icon.png
ApacheServer24ZhongwenWendang/img/save.png
ApacheServer24ZhongwenWendang/img/saved.png
ApacheServer24ZhongwenWendang/img/settings-s.png
ApacheServer24ZhongwenWendang/img/settings.png
ApacheServer24ZhongwenWendang/img/star.png
ApacheServer24ZhongwenWendang/js/__init__.py
ApacheServer24ZhongwenWendang/js/epub.js
ApacheServer24ZhongwenWendang/js/epub.min.js
ApacheServer24ZhongwenWendang/js/epub.min.map
ApacheServer24ZhongwenWendang/js/hooks.min.js
ApacheServer24ZhongwenWendang/js/hooks.min.map
ApacheServer24ZhongwenWendang/js/reader.js
ApacheServer24ZhongwenWendang/js/reader.js.map
ApacheServer24ZhongwenWendang/js/reader.min.js
ApacheServer24ZhongwenWendang/js/reader.min.map
ApacheServer24ZhongwenWendang/js/hooks/__init__.py
ApacheServer24ZhongwenWendang/js/hooks/extensions/__init__.py
ApacheServer24ZhongwenWendang/js/hooks/extensions/highlight.js
apache_server_2_4_zhongwen_wendang-2024.3.4.0.dist-info/METADATA
apache_server_2_4_zhongwen_wendang-2024.3.4.0.dist-info/WHEEL
apache_server_2_4_zhongwen_wendang-2024.3.4.0.dist-info/entry_points.txt
apache_server_2_4_zhongwen_wendang-2024.3.4.0.dist-info/top_level.txt
apache_server_2_4_zhongwen_wendang-2024.3.4.0.dist-info/RECORD
